pybotarena/__init__.py
pybotarena-0.1.0.dist-info/METADATA
pybotarena-0.1.0.dist-info/WHEEL
pybotarena-0.1.0.dist-info/licenses/LICENSE
pybotarena-0.1.0.dist-info/RECORD
