Metadata-Version: 2.1
Name: pybotarena
Version: 0.1.0
Summary: Package to control robot in PybotARena App.
Author-email: Chung Zhi Wei <zhiwei_chung@sutd.edu.sg>, Oka Kurniawan <oka_kurniawan@sutd.edu.sg>
License-File: LICENSE
Classifier: License :: OSI Approved :: MIT License
Classifier: Operating System :: OS Independent
Classifier: Programming Language :: Python :: 3
Requires-Python: >=3.7
